LICENSE.txt
MANIFEST.in
README.md
requirements.txt
setup.py
polaroidme/__init__.py
polaroidme/__main__.py
polaroidme/helpers.py
polaroidme/polaroidme
polaroidme/polaroidme.conf
polaroidme/polaroidme.py
polaroidme.egg-info/PKG-INFO
polaroidme.egg-info/SOURCES.txt
polaroidme.egg-info/dependency_links.txt
polaroidme.egg-info/requires.txt
polaroidme.egg-info/top_level.txt
polaroidme/fonts/HandWri2.ttf
polaroidme/fonts/Handwriting.ttf
polaroidme/fonts/JakesHandwriting.ttf
polaroidme/fonts/MiasScribblings~.ttf
polaroidme/fonts/Outwrite.ttf
polaroidme/fonts/README
polaroidme/fonts/aAutoSignature.otf
polaroidme/fonts/aAutoSignature.ttf
polaroidme/fonts/arial_narrow_7.readme.txt
polaroidme/fonts/arial_narrow_7.ttf
polaroidme/fonts/arial_narrow_7_screen.png
polaroidme/fonts/contrast.ttf
polaroidme/fonts/default.ttf
polaroidme/fonts/raustila-Regular.otf
polaroidme/fonts/raustila-Regular.ttf
polaroidme/fonts/raustila.png
polaroidme/fonts/smallbars.ttf
polaroidme/templates/README