Metadata-Version: 1.1
Name: polaroidme
Version: 0.9.32
Summary: converts an image into vintage polaroid style
Home-page: https://github.com/s3h10r/polaroidme
Author: Sven Hessenmüller
Author-email: sven.hessenmueller@gmail.com
License: UNKNOWN
Platform: UNKNOWN
Classifier: Programming Language :: Python :: 3
Classifier: License :: OSI Approved :: MIT License
Classifier: Operating System :: OS Independent
Classifier: Development Status :: 4 - Beta
Classifier: Environment :: Console
Classifier: Topic :: Multimedia :: Graphics
Classifier: Topic :: Utilities
